verilog_project/src/counter.v
module counter(
    input clk,
    input rst,
    output reg [3:0] count
);

always @(posedge clk or posedge rst) begin
    if (rst)
        count <= 0;
    else
        count <= count + 1;
end

endmodule

verilog_project/tb/counter_tb.v
`timescale 1ns/1ps

module counter_tb;

reg clk;
reg rst;
wire [3:0] count;

counter uut (
    .clk(clk),
    .rst(rst),
    .count(count)
);

always #5 clk = ~clk;

initial begin
    $dumpfile("wave.vcd");
    $dumpvars(0, counter_tb);

    clk = 0;
    rst = 1;

    #10 rst = 0;

    #100 $finish;
end

endmodule

verilog_project/wave.vcd
$date
	Wed Mar 04 21:56:43 2026
$end
$version
	Icarus Verilog
$end
$timescale
	1ps
$end
$scope module counter_tb $end
$var wire 4 ! count [3:0] $end
$var reg 1 " clk $end
$var reg 1 # rst $end
$scope module uut $end
$var wire 1 " clk $end
$var wire 1 # rst $end
$var reg 4 $ count [3:0] $end
$upscope $end
$upscope $end
$enddefinitions $end
$comment Show the parameter values. $end
$dumpall
$end
#0
$dumpvars
b0 $
1#
0"
b0 !
$end
#5000
1"
#10000
0"
0#
#15000
b1 !
b1 $
1"
#20000
0"
#25000
b10 !
b10 $
1"
#30000
0"
#35000
b11 !
b11 $
1"
#40000
0"
#45000
b100 !
b100 $
1"
#50000
0"
#55000
b101 !
b101 $
1"
#60000
0"
#65000
b110 !
b110 $
1"
#70000
0"
#75000
b111 !
b111 $
1"
#80000
0"
#85000
b1000 !
b1000 $
1"
#90000
0"
#95000
b1001 !
b1001 $
1"
#100000
0"
#105000
b1010 !
b1010 $
1"
